schp/__init__.py
schp/evaluate.py
schp/model.py
schp/simple_extractor.py
schp/train.py
schp/datasets/__init__.py
schp/datasets/datasets.py
schp/datasets/simple_extractor_dataset.py
schp/datasets/target_generation.py
schp/modules/__init__.py
schp/modules/bn.py
schp/modules/deeplab.py
schp/modules/dense.py
schp/modules/functions.py
schp/modules/misc.py
schp/modules/residual.py
schp/modules/src/checks.h
schp/modules/src/inplace_abn.cpp
schp/modules/src/inplace_abn.h
schp/modules/src/inplace_abn_cpu.cpp
schp/modules/src/inplace_abn_cuda.cu
schp/modules/src/inplace_abn_cuda_half.cu
schp/modules/src/utils/checks.h
schp/modules/src/utils/common.h
schp/modules/src/utils/cuda.cuh
schp/networks/AugmentCE2P.py
schp/networks/__init__.py
schp/utils/__init__.py
schp/utils/consistency_loss.py
schp/utils/criterion.py
schp/utils/encoding.py
schp/utils/kl_loss.py
schp/utils/lovasz_softmax.py
schp/utils/miou.py
schp/utils/schp.py
schp/utils/soft_dice_loss.py
schp/utils/transforms.py
schp/utils/warmup_scheduler.py
schp-0.1.dist-info/LICENSE
schp-0.1.dist-info/METADATA
schp-0.1.dist-info/WHEEL
schp-0.1.dist-info/top_level.txt
schp-0.1.dist-info/RECORD
